paper_portfolio/__init__.py
paper_portfolio/config_parser.py
paper_portfolio/manager.py
paper_portfolio/run_pipeline.py
paper_portfolio/evaluation/__init__.py
paper_portfolio/evaluation/metrics.py
paper_portfolio/evaluation/reporter.py
paper_portfolio-0.1.1.dist-info/METADATA
paper_portfolio-0.1.1.dist-info/WHEEL
paper_portfolio-0.1.1.dist-info/entry_points.txt
paper_portfolio-0.1.1.dist-info/licenses/LICENSE
paper_portfolio-0.1.1.dist-info/RECORD
