Metadata-Version: 2.4
Name: paper-portfolio
Version: 0.1.1
Summary: A portfolio construction and analysis tool for asset-pricing strategies.
Author-email: Lorenzo Varese <55581163+lorenzovarese@users.noreply.github.com>
License-File: LICENSE
Requires-Python: >=3.11
Requires-Dist: matplotlib>=3.10.0
Requires-Dist: polars>=1.30.0
Requires-Dist: pydantic>=2.11.5
Requires-Dist: pyyaml>=6.0.2
